poetry_bumpversion/__init__.py
poetry_bumpversion/models.py
poetry_bumpversion/plugin.py
poetry_bumpversion/py.typed
poetry_bumpversion-0.3.3.dist-info/LICENSE
poetry_bumpversion-0.3.3.dist-info/METADATA
poetry_bumpversion-0.3.3.dist-info/WHEEL
poetry_bumpversion-0.3.3.dist-info/entry_points.txt
poetry_bumpversion-0.3.3.dist-info/RECORD
