Metadata-Version: 2.3
Name: poetry-bumpversion
Version: 0.3.3
Summary: Poetry plugin to update __version__ in __init__ file and other files containing version strings
License: MIT
Keywords: poetry,bump,version,plugin
Author: Abdul Monim
Author-email: 6266677+monim67@users.noreply.github.com
Requires-Python: >=3.9,<4
Classifier: Typing :: Typed
Requires-Dist: poetry (>=1.2.0,<3)
Requires-Dist: pydantic
Requires-Dist: typing-extensions
